setup.py
bs_orm/DataTypes.py
bs_orm/Requests.py
bs_orm/__init__.py
bs_orm/db_settings.py
bs_orm.egg-info/PKG-INFO
bs_orm.egg-info/SOURCES.txt
bs_orm.egg-info/dependency_links.txt
bs_orm.egg-info/top_level.txt
bs_orm/logic_assistent/__init__.py
bs_orm/logic_assistent/base_function.py
bs_orm/logic_assistent/composit_function.py