Metadata-Version: 2.1
Name: bs-orm
Version: 0.9.1
Summary: best simple orm
Home-page: https://github.com/Jost221/python-orm.git
Author: Jost221
Author-email: mr.z.75@mail.ru
Classifier: Programming Language :: Python :: 3.8
Classifier: License :: OSI Approved :: MIT License
Classifier: Operating System :: OS Independent
Requires-Python: >=3.6
